overture_maps_geoparquet_package/__init__.py
overture_maps_geoparquet_package/overture_downloader.py
overture_maps_geoparquet_package-0.1.2.dist-info/LICENSE
overture_maps_geoparquet_package-0.1.2.dist-info/METADATA
overture_maps_geoparquet_package-0.1.2.dist-info/WHEEL
overture_maps_geoparquet_package-0.1.2.dist-info/entry_points.txt
overture_maps_geoparquet_package-0.1.2.dist-info/RECORD
